scrapegoat/__init__.py
scrapegoat/main.py
scrapegoat/utils.py
scrapegoat-1.0.0.7.dist-info/LICENSE.txt
scrapegoat-1.0.0.7.dist-info/METADATA
scrapegoat-1.0.0.7.dist-info/WHEEL
scrapegoat-1.0.0.7.dist-info/top_level.txt
scrapegoat-1.0.0.7.dist-info/RECORD
