Metadata-Version: 2.1
Name: scrapegoat
Version: 1.0.0.7
Summary: Scrape data in one-shot
Home-page: https://github.com/Scrape-Goat/scrapegoat
Author: Navaneeth
Author-email: scrapegoat.python@gmail.com
License: UNKNOWN
Platform: UNKNOWN
Classifier: Programming Language :: Python :: 3
Classifier: License :: OSI Approved :: MIT License
Classifier: Operating System :: OS Independent
Requires-Python: >=3.6
License-File: LICENSE.txt
Requires-Dist: GoogleNews (>=1.5.9)
Requires-Dist: googletrans (>=3.1.0a0)
Requires-Dist: scipy (>=1.7.1)
Requires-Dist: beautifulsoup4 (>=4.9.3)
Requires-Dist: numpy (>=1.21.1)
Requires-Dist: pandas (>=1.1.5)
Requires-Dist: Wikipedia-API (>=0.5.4)
Requires-Dist: sentence-transformers
Requires-Dist: google
Requires-Dist: tqdm
